epregistry/__init__.py
epregistry/epregistry.py
epregistry/package_to_distribution.py
epregistry/py.typed
epregistry-2.0.2.dist-info/WHEEL
epregistry-2.0.2.dist-info/METADATA
epregistry-2.0.2.dist-info/RECORD
