Metadata-Version: 2.3
Name: epregistry
Version: 2.0.2
Summary: A registry for entry points (cached and generically typed)
Keywords: 
Author: Philipp Temminghoff
Author-email: Philipp Temminghoff <philipptemminghoff@googlemail.com>
License: MIT License
Classifier: Development Status :: 4 - Beta
Classifier: Intended Audience :: Developers
Classifier: Operating System :: OS Independent
Classifier: Programming Language :: Python :: 3
Classifier: Programming Language :: Python :: 3 :: Only
Classifier: Programming Language :: Python :: 3.12
Classifier: Programming Language :: Python :: 3.13
Classifier: Programming Language :: Python :: 3.14
Classifier: Topic :: Documentation
Classifier: Topic :: Software Development
Classifier: Topic :: Utilities
Classifier: Typing :: Typed
Requires-Dist: typing-extensions>=4.12.2
Requires-Python: >=3.13
Project-URL: Code coverage, https://app.codecov.io/gh/phil65/epregistry
Project-URL: Discussions, https://github.com/phil65/epregistry/discussions
Project-URL: Documentation, https://phil65.github.io/epregistry/
Project-URL: Issues, https://github.com/phil65/epregistry/issues
Project-URL: Source, https://github.com/phil65/epregistry
